[
    {
        "%vlocity_namespace%__DomainObjectAPIName__c": "%vlocity_namespace%__CustomerInteraction__c",
        "%vlocity_namespace%__DomainObjectCreationOrder__c": 1,
        "%vlocity_namespace%__DomainObjectFieldAPIName__c": "%vlocity_namespace%__AccountId__c",
        "%vlocity_namespace%__FormulaOrder__c": 0,
        "%vlocity_namespace%__GlobalKey__c": "e6d06ad2-2b83-e827-3c00-561a0d1c4151",
        "%vlocity_namespace%__InterfaceFieldAPIName__c": "resultValueMap:%vlocity_namespace%__PolicyHolderId__c",
        "%vlocity_namespace%__InterfaceObjectName__c": "json",
        "%vlocity_namespace%__IsDisabled__c": false,
        "%vlocity_namespace%__IsRequiredForUpsert__c": false,
        "%vlocity_namespace%__LinkCreatedIndex__c": 0,
        "%vlocity_namespace%__MapId__c": "CreateInteractionForPolicyPrimaryCustoma0J41000000ehS0EAIItem1",
        "%vlocity_namespace%__OMplusSyncEnabled__c": false,
        "%vlocity_namespace%__UpsertKey__c": false,
        "Name": "CreateInteractionForPolicyPrimary",
        "VlocityDataPackType": "SObject",
        "VlocityRecordSObjectType": "%vlocity_namespace%__DRMapItem__c"
    },
    {
        "%vlocity_namespace%__DomainObjectAPIName__c": "%vlocity_namespace%__CustomerInteraction__c",
        "%vlocity_namespace%__DomainObjectCreationOrder__c": 1,
        "%vlocity_namespace%__DomainObjectFieldAPIName__c": "%vlocity_namespace%__VerificationTimestamp__c",
        "%vlocity_namespace%__FormulaOrder__c": 0,
        "%vlocity_namespace%__GlobalKey__c": "37147d85-4967-73ab-c0be-4e7ec34281cf",
        "%vlocity_namespace%__InterfaceFieldAPIName__c": "verificationResult:timestamp",
        "%vlocity_namespace%__InterfaceObjectName__c": "json",
        "%vlocity_namespace%__IsDisabled__c": false,
        "%vlocity_namespace%__IsRequiredForUpsert__c": false,
        "%vlocity_namespace%__LinkCreatedIndex__c": 0,
        "%vlocity_namespace%__MapId__c": "CreateInteractionForPolicyPrimaryCustoma0J41000000ehS0EAIItem3",
        "%vlocity_namespace%__OMplusSyncEnabled__c": false,
        "%vlocity_namespace%__UpsertKey__c": false,
        "Name": "CreateInteractionForPolicyPrimary",
        "VlocityDataPackType": "SObject",
        "VlocityRecordSObjectType": "%vlocity_namespace%__DRMapItem__c"
    },
    {
        "%vlocity_namespace%__DomainObjectAPIName__c": "%vlocity_namespace%__CustomerInteraction__c",
        "%vlocity_namespace%__DomainObjectCreationOrder__c": 1,
        "%vlocity_namespace%__DomainObjectFieldAPIName__c": "%vlocity_namespace%__VerifiedAgentName__c",
        "%vlocity_namespace%__FormulaOrder__c": 0,
        "%vlocity_namespace%__GlobalKey__c": "c79a5657-94b6-a040-521e-0e54431b8aad",
        "%vlocity_namespace%__InterfaceFieldAPIName__c": "verificationResult:username",
        "%vlocity_namespace%__InterfaceObjectName__c": "json",
        "%vlocity_namespace%__IsDisabled__c": false,
        "%vlocity_namespace%__IsRequiredForUpsert__c": false,
        "%vlocity_namespace%__LinkCreatedIndex__c": 0,
        "%vlocity_namespace%__MapId__c": "CreateInteractionForPolicyPrimaryCustoma0J41000000ehS0EAIItem4",
        "%vlocity_namespace%__OMplusSyncEnabled__c": false,
        "%vlocity_namespace%__UpsertKey__c": false,
        "Name": "CreateInteractionForPolicyPrimary",
        "VlocityDataPackType": "SObject",
        "VlocityRecordSObjectType": "%vlocity_namespace%__DRMapItem__c"
    },
    {
        "%vlocity_namespace%__DomainObjectAPIName__c": "%vlocity_namespace%__CustomerInteraction__c",
        "%vlocity_namespace%__DomainObjectCreationOrder__c": 1,
        "%vlocity_namespace%__DomainObjectFieldAPIName__c": "%vlocity_namespace%__Verified__c",
        "%vlocity_namespace%__FormulaOrder__c": 0,
        "%vlocity_namespace%__GlobalKey__c": "1806dceb-2905-dd03-e4fd-039afe5dd020",
        "%vlocity_namespace%__InterfaceFieldAPIName__c": "verificationResult:status",
        "%vlocity_namespace%__InterfaceObjectName__c": "json",
        "%vlocity_namespace%__IsDisabled__c": false,
        "%vlocity_namespace%__IsRequiredForUpsert__c": false,
        "%vlocity_namespace%__LinkCreatedIndex__c": 0,
        "%vlocity_namespace%__MapId__c": "CreateInteractionForPolicyPrimaryCustoma0J41000000ehS0EAIItem2",
        "%vlocity_namespace%__OMplusSyncEnabled__c": false,
        "%vlocity_namespace%__UpsertKey__c": false,
        "Name": "CreateInteractionForPolicyPrimary",
        "VlocityDataPackType": "SObject",
        "VlocityRecordSObjectType": "%vlocity_namespace%__DRMapItem__c"
    },
    {
        "%vlocity_namespace%__DomainObjectAPIName__c": "%vlocity_namespace%__CustomerInteractionTopic__c",
        "%vlocity_namespace%__DomainObjectCreationOrder__c": 2,
        "%vlocity_namespace%__DomainObjectFieldAPIName__c": "%vlocity_namespace%__CustomerInteractionId__c",
        "%vlocity_namespace%__FormulaOrder__c": 0,
        "%vlocity_namespace%__GlobalKey__c": "20b4e7ed-1a67-e219-e096-aeca6ca0d41d",
        "%vlocity_namespace%__InterfaceObjectName__c": "json",
        "%vlocity_namespace%__IsDisabled__c": false,
        "%vlocity_namespace%__IsRequiredForUpsert__c": false,
        "%vlocity_namespace%__LinkCreatedField__c": "Id",
        "%vlocity_namespace%__LinkCreatedIndex__c": 1,
        "%vlocity_namespace%__MapId__c": "CreateInteractionForPolicyPrimaryCustoma0J41000000ehS0EAIItem5",
        "%vlocity_namespace%__OMplusSyncEnabled__c": false,
        "%vlocity_namespace%__UpsertKey__c": false,
        "Name": "CreateInteractionForPolicyPrimary",
        "VlocityDataPackType": "SObject",
        "VlocityRecordSObjectType": "%vlocity_namespace%__DRMapItem__c"
    },
    {
        "%vlocity_namespace%__DomainObjectAPIName__c": "%vlocity_namespace%__CustomerInteractionTopic__c",
        "%vlocity_namespace%__DomainObjectCreationOrder__c": 2,
        "%vlocity_namespace%__DomainObjectFieldAPIName__c": "%vlocity_namespace%__PolicyId__c",
        "%vlocity_namespace%__FormulaOrder__c": 0,
        "%vlocity_namespace%__GlobalKey__c": "c11cad6a-2ea1-57dc-d83a-5428a45136ee",
        "%vlocity_namespace%__InterfaceFieldAPIName__c": "resultValueMap:%vlocity_namespace%__PolicyId__c",
        "%vlocity_namespace%__InterfaceObjectName__c": "json",
        "%vlocity_namespace%__IsDisabled__c": false,
        "%vlocity_namespace%__IsRequiredForUpsert__c": false,
        "%vlocity_namespace%__LinkCreatedIndex__c": 0,
        "%vlocity_namespace%__MapId__c": "CreateInteractionForPolicyPrimaryCustoma0J41000000ehS0EAIItem7",
        "%vlocity_namespace%__OMplusSyncEnabled__c": false,
        "%vlocity_namespace%__UpsertKey__c": false,
        "Name": "CreateInteractionForPolicyPrimary",
        "VlocityDataPackType": "SObject",
        "VlocityRecordSObjectType": "%vlocity_namespace%__DRMapItem__c"
    },
    {
        "%vlocity_namespace%__DomainObjectAPIName__c": "%vlocity_namespace%__CustomerInteractionTopic__c",
        "%vlocity_namespace%__DomainObjectCreationOrder__c": 2,
        "%vlocity_namespace%__DomainObjectFieldAPIName__c": "%vlocity_namespace%__PolicyPartyRelationshipId__c",
        "%vlocity_namespace%__FormulaOrder__c": 0,
        "%vlocity_namespace%__GlobalKey__c": "d3cac36a-ce7c-ba75-e82d-4eb44cdc6d5b",
        "%vlocity_namespace%__InterfaceFieldAPIName__c": "recordId",
        "%vlocity_namespace%__InterfaceObjectName__c": "json",
        "%vlocity_namespace%__IsDisabled__c": false,
        "%vlocity_namespace%__IsRequiredForUpsert__c": false,
        "%vlocity_namespace%__LinkCreatedIndex__c": 0,
        "%vlocity_namespace%__MapId__c": "CreateInteractionForPolicyPrimaryCustoma0J41000000ehS0EAIItem6",
        "%vlocity_namespace%__OMplusSyncEnabled__c": false,
        "%vlocity_namespace%__UpsertKey__c": false,
        "Name": "CreateInteractionForPolicyPrimary",
        "VlocityDataPackType": "SObject",
        "VlocityRecordSObjectType": "%vlocity_namespace%__DRMapItem__c"
    }
]